README.md
setup.py
pyminer_comm/__init__.py
pyminer_comm.egg-info/PKG-INFO
pyminer_comm.egg-info/SOURCES.txt
pyminer_comm.egg-info/dependency_links.txt
pyminer_comm.egg-info/requires.txt
pyminer_comm.egg-info/top_level.txt
pyminer_comm/base/__init__.py
pyminer_comm/base/datadesc.py
pyminer_comm/base/encode_decode.py
pyminer_comm/base/network.py
pyminer_comm/base/sys_utils.py
pyminer_comm/data_client/__init__.py
pyminer_comm/data_client/data_client.py
pyminer_comm/data_client/unittest_data_client.py
pyminer_comm/pyminer_client/__init__.py
pyminer_comm/pyminer_client/pm_client.py